__init__.py
cli.py
nova.py
fixers/__init__.py
fixers/access_controls.py
fixers/imports.py
fixers/xcoms.py
astronomer_nova-0.1.3.dist-info/METADATA
astronomer_nova-0.1.3.dist-info/WHEEL
astronomer_nova-0.1.3.dist-info/entry_points.txt
astronomer_nova-0.1.3.dist-info/top_level.txt
astronomer_nova-0.1.3.dist-info/RECORD
