Metadata-Version: 2.1
Name: astronomer-nova
Version: 0.1.3
Summary: Automate migration from Airflow 1 to Airflow 2
Keywords: Airflow,Migration
Classifier: Framework :: Apache Airflow
Classifier: Programming Language :: Python :: 3
Requires-Python: <4,>=3.9
Requires-Dist: redbaron (==0.9.2)
Requires-Dist: flake8 (==5.0.4)
Provides-Extra: lint
Requires-Dist: black (==22.10.0) ; extra == 'lint'
Requires-Dist: flake8 (==5.0.4) ; extra == 'lint'
Requires-Dist: isort (==5.10.1) ; extra == 'lint'
Requires-Dist: mypy (==0.991) ; extra == 'lint'
Requires-Dist: pyright ; extra == 'lint'
Provides-Extra: test
Requires-Dist: apache-airflow (==2.4.3) ; extra == 'test'
Requires-Dist: pytest (==7.1.3) ; extra == 'test'
Requires-Dist: pytest-cov (==4.0.0) ; extra == 'test'
